eyelogic/ELApi.py
eyelogic/__init__.py
eyelogic/x64/ELApi.dll
eyelogic/x64/ELCApi.dll
eyelogic/x86/ELApi32.dll
eyelogic/x86/ELCApi32.dll
eyelogic_sdk-1.2.0.dist-info/licenses/LICENSE
eyelogic_sdk-1.2.0.dist-info/METADATA
eyelogic_sdk-1.2.0.dist-info/WHEEL
eyelogic_sdk-1.2.0.dist-info/top_level.txt
eyelogic_sdk-1.2.0.dist-info/RECORD
