Metadata-Version: 2.4
Name: eyelogic-sdk
Version: 1.2.0
Summary: Python wrapper for the EyeLogic eye tracking API
Home-page: https://www.eyelogic.de
Author: EyeLogic GmbH
Author-email: info@eyelogic.de
Classifier: Programming Language :: Python :: 3
Classifier: Natural Language :: English
Classifier: License :: Freely Distributable
Classifier: Operating System :: Microsoft :: Windows :: Windows 10
Requires-Python: >=3.6
License-File: LICENSE
Dynamic: author
Dynamic: author-email
Dynamic: classifier
Dynamic: description
Dynamic: description-content-type
Dynamic: home-page
Dynamic: license-file
Dynamic: requires-python
Dynamic: summary
